johnstondechazal/__init__.py
johnstondechazal/_version.py
johnstondechazal/cli.py
johnstondechazal/data.py
johnstondechazal-0.0.0.dist-info/AUTHORS.rst
johnstondechazal-0.0.0.dist-info/LICENSE
johnstondechazal-0.0.0.dist-info/METADATA
johnstondechazal-0.0.0.dist-info/WHEEL
johnstondechazal-0.0.0.dist-info/entry_points.txt
johnstondechazal-0.0.0.dist-info/top_level.txt
johnstondechazal-0.0.0.dist-info/RECORD
