Metadata-Version: 2.1
Name: johnstondechazal
Version: 0.0.0
Summary: A method of optimising facial landmark selection from crowd sourced labels.
Home-page: https://github.com/docEbrown/johnstondechazal
Author: Ben Johnston
Author-email: docEbrown_github@protonmail.com
License: GNU General Public License v3
Keywords: johnstondechazal
Platform: UNKNOWN
Classifier: Development Status :: 2 - Pre-Alpha
Classifier: Intended Audience :: Developers
Classifier: License :: OSI Approved :: GNU General Public License v3 (GPLv3)
Classifier: Natural Language :: English
Classifier: Programming Language :: Python :: 3
Classifier: Programming Language :: Python :: 3.5
Classifier: Programming Language :: Python :: 3.6
Classifier: Programming Language :: Python :: 3.7
Classifier: Programming Language :: Python :: 3.8
Requires-Python: >=3.5
Requires-Dist: Click (>=7.0)
